[
  {
    "source_id": "support_knowledge",
    "name": "Support Knowledge",
    "owner": "it_support",
    "classification": "internal",
    "trust_level": "approved",
    "allowed_capabilities": ["retrieve_best_knowledge"],
    "allowed_goal_categories": ["operational_troubleshooting"],
    "source_role": "primary",
    "required_controls": [
      "log_source_access",
      "return_knowledge_quality_score",
      "check_last_validated_date"
    ],
    "metadata_complete": true,
    "high_impact_signals": []
  },
  {
    "source_id": "wiki_knowledge",
    "name": "Engineering Wiki Knowledge",
    "owner": "engineering_enablement",
    "classification": "internal",
    "trust_level": "conditional",
    "allowed_capabilities": ["retrieve_best_knowledge"],
    "allowed_goal_categories": ["operational_troubleshooting", "self_help"],
    "source_role": "supporting",
    "required_controls": [
      "log_source_access",
      "corroborating_evidence_required"
    ],
    "metadata_complete": true,
    "high_impact_signals": []
  },
  {
    "source_id": "self_help_knowledge",
    "name": "Self Help Knowledge",
    "owner": "employee_experience",
    "classification": "internal",
    "trust_level": "approved",
    "allowed_capabilities": ["retrieve_best_knowledge"],
    "allowed_goal_categories": ["self_help"],
    "source_role": "primary",
    "required_controls": [
      "log_source_access",
      "return_knowledge_quality_score"
    ],
    "metadata_complete": true,
    "high_impact_signals": []
  },
  {
    "source_id": "human_resources_knowledge",
    "name": "Human Resources Knowledge",
    "owner": "human_resources",
    "classification": "confidential",
    "trust_level": "approved",
    "allowed_capabilities": ["retrieve_best_knowledge"],
    "allowed_goal_categories": ["hr_support"],
    "source_role": "restricted",
    "required_controls": [
      "log_source_access",
      "human_review",
      "least_privilege"
    ],
    "metadata_complete": true,
    "high_impact_signals": ["employment_context"]
  },
  {
    "source_id": "employee_identification_knowledge",
    "name": "Employee Identification Knowledge",
    "owner": "identity_and_access_management",
    "classification": "restricted",
    "trust_level": "approved",
    "allowed_capabilities": ["retrieve_identity_context"],
    "allowed_goal_categories": ["hr_support"],
    "source_role": "restricted",
    "required_controls": [
      "business_justification_required",
      "human_review",
      "least_privilege",
      "audit_required"
    ],
    "metadata_complete": true,
    "high_impact_signals": ["identity_data"]
  },
  {
    "source_id": "validated_learning_store",
    "name": "Validated Learning Store",
    "owner": "enterprise_learning",
    "classification": "internal",
    "trust_level": "approved",
    "allowed_capabilities": ["write_validated_learning"],
    "allowed_goal_categories": [
      "operational_troubleshooting",
      "self_help",
      "hr_support"
    ],
    "source_role": "write_target",
    "required_controls": [
      "human_approval",
      "source_owner_review",
      "audit_required"
    ],
    "metadata_complete": true,
    "high_impact_signals": []
  },
  {
    "source_id": "incomplete_operational_source",
    "name": "Incomplete Operational Source",
    "owner": null,
    "classification": "internal",
    "trust_level": "unknown",
    "allowed_capabilities": ["retrieve_best_knowledge"],
    "allowed_goal_categories": ["operational_troubleshooting"],
    "source_role": "governance_debt_test",
    "required_controls": [],
    "metadata_complete": false,
    "high_impact_signals": []
  },
  {
    "source_id": "high_impact_incomplete_source",
    "name": "High Impact Incomplete Source",
    "owner": null,
    "classification": "restricted",
    "trust_level": "unknown",
    "allowed_capabilities": ["retrieve_best_knowledge"],
    "allowed_goal_categories": ["operational_troubleshooting"],
    "source_role": "high_risk_uncertainty_test",
    "required_controls": [],
    "metadata_complete": false,
    "high_impact_signals": ["business_critical_service"]
  }
]